brutefir/__init__.py
brutefir/brutefir.py
brutefir/gen_config.py
brutefir-0.0.5.dist-info/LICENSE
brutefir-0.0.5.dist-info/METADATA
brutefir-0.0.5.dist-info/WHEEL
brutefir-0.0.5.dist-info/entry_points.txt
brutefir-0.0.5.dist-info/top_level.txt
brutefir-0.0.5.dist-info/RECORD
