Metadata-Version: 2.1
Name: brutefir
Version: 0.0.5
Summary: Python library to control BruteFIR
Home-page: https://github.com/auchter/python-brutefir
Author: Michael Auchter
Author-email: a@phire.org
Project-URL: Bug Tracker, https://github.com/auchter/python-brutefir/issues
Classifier: Programming Language :: Python :: 3
Classifier: License :: OSI Approved :: MIT License
Classifier: Operating System :: OS Independent
Requires-Python: >=3.6
License-File: LICENSE
Requires-Dist: numpy
Requires-Dist: pexpect
Requires-Dist: pyyaml
Requires-Dist: scipy
Requires-Dist: voluptuous
